scatterplot/__init__.py
scatterplot/main.py
scatterplot/scatterplot.py
tests/__init__.py
tests/test_scatterplot.py
scatterplot-0.1.0.dist-info/METADATA
scatterplot-0.1.0.dist-info/WHEEL
scatterplot-0.1.0.dist-info/top_level.txt
scatterplot-0.1.0.dist-info/RECORD
