Metadata-Version: 2.1
Name: scatterplot
Version: 0.1.0
Summary: A customizable scatter plot package
Home-page: https://github.com/samehsalah
Author: Sameh Salah
Author-email: samehsalah83@gmail.com
Classifier: Programming Language :: Python :: 3
Classifier: License :: OSI Approved :: MIT License
Classifier: Operating System :: OS Independent
Requires-Python: >=3.6
Requires-Dist: matplotlib (>=3.0.0)
Requires-Dist: numpy
